ApplicationInsightsAnalyticsClient-Python.pyproj
ApplicationInsightsAnalyticsClient-Python.sln
LICENSE.txt
MANIFEST.in
README.rst
setup.cfg
setup.py
aianalytics_client.egg-info/PKG-INFO
aianalytics_client.egg-info/SOURCES.txt
aianalytics_client.egg-info/dependency_links.txt
aianalytics_client.egg-info/requires.txt
aianalytics_client.egg-info/top_level.txt
analytics/__init__.py
analytics/client.py