Metadata-Version: 1.1
Name: aianalytics-client
Version: 0.1.5
Summary: This project enables quering the Application Insights Analytics API while parsing the results for furthur processing using data analysis tools, such as numpy
Home-page: https://github.com/asafst/ApplicationInsightsAnalyticsClient-Python
Author: Asaf Strassberg
Author-email: asafst@microsoft.com
License: MIT
Download-URL: https://github.com/asafst/ApplicationInsightsAnalyticsClient-Python
Keywords: analytics applicationinsights telemetry appinsights numpy IPython
Platform: UNKNOWN
Classifier: Development Status :: 4 - Beta
Classifier: Intended Audience :: Science/Research
Classifier: Intended Audience :: Developers
Classifier: Topic :: Scientific/Engineering :: Information Analysis
Classifier: Topic :: Software Development :: Libraries :: Python Modules
Classifier: Operating System :: OS Independent
Classifier: License :: OSI Approved :: MIT License
Classifier: Programming Language :: Python :: 2.7
Classifier: Programming Language :: Python :: 3.5
